README.rst
setup.py
gdom/__init__.py
gdom/cmd.py
gdom/schema.py
gdom.egg-info/PKG-INFO
gdom.egg-info/SOURCES.txt
gdom.egg-info/dependency_links.txt
gdom.egg-info/entry_points.txt
gdom.egg-info/requires.txt
gdom.egg-info/top_level.txt