Metadata-Version: 1.1
Name: gdom
Version: 0.1.1
Summary: DOM Traversing and Scraping using GraphQL
Home-page: http://github.com/syrusakbary/gdom
Author: Syrus Akbary
Author-email: me@syrusakbary.com
License: MIT
Download-URL: git@github.com:syrusakbary/gdom.git
Keywords: scraping html graphql json
Platform: UNKNOWN
